pyrmle/__init__.py
pyrmle/pyrmle.py
pyrmle/pyrmle_hfuncs.py
pyrmle-0.0.3.post9.dist-info/LICENSE
pyrmle-0.0.3.post9.dist-info/METADATA
pyrmle-0.0.3.post9.dist-info/WHEEL
pyrmle-0.0.3.post9.dist-info/top_level.txt
pyrmle-0.0.3.post9.dist-info/RECORD
