Metadata-Version: 2.1
Name: pyrmle
Version: 0.0.3.post9
Summary: Python package for implementing Regularized Maximum Likelihood for Random Coefficient Models
Home-page: https://github.com/eae-mendoza/PyRMLE
Author: Mendoza, E.
Author-email: emil.edgar.mendoza@gmail.com
License: BSD
Platform: UNKNOWN
Classifier: License :: OSI Approved :: BSD License
Classifier: Programming Language :: Python :: 3
Classifier: Programming Language :: Python :: 3.7
Classifier: Programming Language :: Python :: 3.8
Classifier: Programming Language :: Python :: 3.9
Requires-Dist: scipy
Requires-Dist: sklearn
Requires-Dist: matplotlib
